rmnn/__init__.py
rmnn/apps.py
rmnn/represent/__init__.py
rmnn/represent/inr.py
rmnn/represent/loss.py
rmnn/represent/mfn.py
rmnn/represent/module.py
rmnn/represent/opt.py
rmnn/represent/reg.py
rmnn/represent/representer.py
rmnn/represent/siren.py
rmnn/represent/splitinr.py
rmnn/toolbox/__init__.py
rmnn/toolbox/data_display.py
rmnn/toolbox/data_io.py
rmnn/toolbox/dataloader.py
rmnn/toolbox/gen_mask.py
rmnn/toolbox/noise.py
rmnn/toolbox/wrapper.py
rmnn-0.0.2.dist-info/LICENSE
rmnn-0.0.2.dist-info/METADATA
rmnn-0.0.2.dist-info/WHEEL
rmnn-0.0.2.dist-info/top_level.txt
rmnn-0.0.2.dist-info/RECORD
