Metadata-Version: 2.1
Name: rmnn
Version: 0.0.2
Summary: A small package for represent tensors or matrix with neural network based on Pytorch
Home-page: https://gitee.com/lizhemin15/rmnn-pip
Author: Zhemin Li
Author-email: lizhemin15@163.com
License: GPL-3.0
Download-URL: https://gitee.com/lizhemin15/rmnn-pip
Keywords: matrix representation
Platform: UNKNOWN
Classifier: Development Status :: 3 - Alpha
Classifier: Intended Audience :: Science/Research
Classifier: Intended Audience :: Developers
Classifier: Programming Language :: Python
Classifier: Topic :: Software Development
Classifier: Topic :: Scientific/Engineering
License-File: LICENSE
Requires-Dist: numpy
Requires-Dist: torch
Requires-Dist: scipy
Requires-Dist: scikit-learn
Provides-Extra: dev
Requires-Dist: pylint ; extra == 'dev'
Requires-Dist: sphinx ; extra == 'dev'
Provides-Extra: test
